dotpy/__init__.py
dotpy/components/__init__.py
dotpy/components/attribute.py
dotpy/components/attribute_statement.py
dotpy/components/digraph.py
dotpy/components/edge.py
dotpy/components/node.py
dotpy/parser/__init__.py
dotpy/parser/lexer.py
dotpy/parser/parser.py
dotpy/parser/parsetab.py
dotpy-0.0.2.dist-info/METADATA
dotpy-0.0.2.dist-info/RECORD
dotpy-0.0.2.dist-info/WHEEL
dotpy-0.0.2.dist-info/top_level.txt
